toomanyfiles/__init__.py
toomanyfiles/locale/es/LC_MESSAGES/toomanyfiles.mo
toomanyfiles/locale/es.po
toomanyfiles/locale/toomanyfiles.pot
toomanyfiles/poethepoet.py
toomanyfiles/tests/test_poethepoet.py
toomanyfiles/tests/test_toomanyfiles.py
toomanyfiles/toomanyfiles.py
toomanyfiles/types.py
toomanyfiles-1.1.0.dist-info/METADATA
toomanyfiles-1.1.0.dist-info/WHEEL
toomanyfiles-1.1.0.dist-info/entry_points.txt
toomanyfiles-1.1.0.dist-info/licenses/LICENSE.txt
toomanyfiles-1.1.0.dist-info/RECORD
