Metadata-Version: 2.4
Name: toomanyfiles
Version: 1.1.0
Summary: Remove files and directories with date and time patterns
License: GPL-3
License-File: LICENSE.txt
Author: y
Requires-Python: >=3.11,<4
Classifier: License :: Other/Proprietary License
Classifier: Programming Language :: Python :: 3
Classifier: Programming Language :: Python :: 3.11
Classifier: Programming Language :: Python :: 3.12
Classifier: Programming Language :: Python :: 3.13
Classifier: Programming Language :: Python :: 3.14
Requires-Dist: colorama (>=0.4.6)
Requires-Dist: pydicts (>=1.1.0)
Project-URL: Homepage, https://github.com/turulomio/toomanyfiles/
Project-URL: Repository, https://github.com/turulomio/toomanyfiles/
Project-URL: changelog, https://github.com/turulomio/toomanyfiles#changelog
